airt/__init__.py
airt/_modidx.py
airt/_components/__init__.py
airt/_components/helpers.py
airt/_components/mono_dense_layer.py
airt/keras/__init__.py
airt/keras/experiments.py
airt/keras/layers/__init__.py
monotonic_nn-0.3.5.dist-info/LICENSE
monotonic_nn-0.3.5.dist-info/METADATA
monotonic_nn-0.3.5.dist-info/WHEEL
monotonic_nn-0.3.5.dist-info/entry_points.txt
monotonic_nn-0.3.5.dist-info/top_level.txt
monotonic_nn-0.3.5.dist-info/RECORD
