Metadata-Version: 2.1
Name: monotonic-nn
Version: 0.3.5
Summary: Monotonic Neural Networks
Home-page: https://github.com/airtai/monotonic-nn
Author: AIRT Technologies d.o.o.
Author-email: info@airt.ai
License: Creative Commons License
Project-URL: Bug Tracker, https://github.com/airtai/monotonic-nn/issues
Project-URL: CI, https://github.com/airtai/monotonic-nn/actions
Project-URL: Documentation, https://monotonic.airt.ai/
Project-URL: Tutorial, https://colab.research.google.com/github/airtai/monotonic-nn/blob/main/nbs/index.ipynb
Keywords: tensorflow keras monotone "monotonic neural networks" "dense layer"
Platform: UNKNOWN
Classifier: Development Status :: 5 - Production/Stable
Classifier: Intended Audience :: Developers
Classifier: Natural Language :: English
Classifier: Programming Language :: Python :: 3.9
Classifier: Programming Language :: Python :: 3.10
Classifier: Programming Language :: Python :: 3.11
Classifier: License :: Free for non-commercial use
Requires-Python: >=3.9
License-File: LICENSE
Requires-Dist: tensorflow<2.16,>=2.10.0
Provides-Extra: dev
Requires-Dist: nbdev-mkdocs==0.6.1; extra == "dev"
Requires-Dist: pytest==8.3.5; extra == "dev"
Requires-Dist: pandas==2.2.3; extra == "dev"
Requires-Dist: nbqa==1.9.1; extra == "dev"
Requires-Dist: black==25.1.0; extra == "dev"
Requires-Dist: isort==6.0.1; extra == "dev"
Requires-Dist: matplotlib>=3.9; extra == "dev"
Requires-Dist: seaborn==0.13.2; extra == "dev"
Requires-Dist: mypy==1.15.0; extra == "dev"
Requires-Dist: bandit==1.8.3; extra == "dev"
Requires-Dist: semgrep==1.112.0; extra == "dev"
Requires-Dist: tqdm==4.67.1; extra == "dev"
Requires-Dist: numpy<2; extra == "dev"
Requires-Dist: keras-tuner[bayesian]==1.3.5; extra == "dev"
Provides-Extra: experiments
Requires-Dist: keras-tuner[bayesian]==1.3.5; extra == "experiments"
